{
    "internacional": [
        {
            "name": "France24 Español",
            "url": "https://www.france24.com/es/rss"
        },
        {
            "name": "Le Monde International",
            "url": "https://www.lemonde.fr/rss/en_continu.xml"
        },
        {
            "name": "BBC Mundo",
            "url": "https://feeds.bbci.co.uk/mundo/rss.xml"
        },
        {
            "name": "Reuters Top News",
            "url": "http://feeds.reuters.com/reuters/topNews"
        },
        {
            "name": "Le Figaro",
            "url": "https://www.lefigaro.fr/rss/figaro_actualites.xml"
        }
    ],
    "nacional": [
        {
            "name": "La Tercera",
            "url": "https://www.latercera.com/rss/"
        },
        {
            "name": "CIPER Chile",
            "url": "https://www.ciperchile.cl/feed/"
        }
    ],
    "opinion_ensayo": [
        {
            "name": "Jacobin América Latina",
            "url": "https://jacobinlat.com/feed/"
        },
        {
            "name": "The Guardian Opinion",
            "url": "https://www.theguardian.com/uk/commentisfree/rss"
        },
        {
            "name": "El País Opinión",
            "url": "https://feeds.elpais.com/mrss-s/pages/ep/site/elpais.com/section/opinion/portada"
        }
    ],
    "ciencia_tecnologia": [
        {
            "name": "Sciences et Avenir",
            "url": "https://www.sciencesetavenir.fr/rss.xml"
        },
        {
            "name": "Nature Current",
            "url": "http://feeds.nature.com/nature/rss/current?x=1"
        }
    ],
    "cultura_arte": [
        {
            "name": "The Guardian Culture",
            "url": "https://www.theguardian.com/uk/culture/rss"
        },
        {
            "name": "El País Cultura",
            "url": "https://feeds.elpais.com/mrss-s/pages/ep/site/elpais.com/section/cultura/portada"
        },
        {
            "name": "Revista Ñ – Clarín Cultura",
            "url": "https://www.clarin.com/rss/cultura/"
        }
    ]
}